cppython_core/__init__.py
cppython_core/exceptions.py
cppython_core/plugin_schema/__init__.py
cppython_core/plugin_schema/generator.py
cppython_core/plugin_schema/provider.py
cppython_core/plugin_schema/scm.py
cppython_core/py.typed
cppython_core/resolution.py
cppython_core/schema.py
cppython_core/utility.py
cppython_core-0.7.0.dist-info/WHEEL
cppython_core-0.7.0.dist-info/METADATA
cppython_core-0.7.0.dist-info/licenses/LICENSE.md
cppython_core-0.7.0.dist-info/RECORD
