Metadata-Version: 2.1
Name: cppython-core
Version: 0.7.0
Summary: Data definitions for CPPython
License: MIT
Author-email: Synodic Software <contact@synodic.software>
Requires-Python: >=3.11
Requires-Dist: pydantic>=2.0b1
Project-URL: homepage, https://github.com/Synodic-Software/CPPython-Core
Project-URL: repository, https://github.com/Synodic-Software/CPPython-Core
